Metadata-Version: 1.0
Name: distributions-class
Version: 1.2
Summary: Gaussian and binomial distributions
Home-page: UNKNOWN
Author: Alabi jide
Author-email: alabijide800@gmail.com
License: UNKNOWN
Platform: UNKNOWN
